[
    {
      "id": "E1",
      "title": "CCTV Evidence",
      "type": "image",
      "slotType": "OPPORTUNITY",
      "revealedWhen": "event.timeline_reconstruction",
      "summaryTemplate": "CCTV shows [SUSPECT_NAME] near the scene at the critical time",
      "assignment": {
        "targetCount": 4,
        "filters": ["canBeKiller=true"],
        "exclusive": false
      }
    },
    {
      "id": "E2",
      "title": "Physical Evidence",
      "type": "object",
      "slotType": "PHYSICAL_LINK",
      "revealedWhen": "event.scene_analysis",
      "summaryTemplate": "Item belonging to [SUSPECT_NAME] found at the crime scene",
      "assignment": {
        "targetCount": 1,
        "filters": ["canBeKiller=true"],
        "exclusive": true
      }
    },
    {
        "id": "E3",
        "title": "Handwritten Envelope",
        "type": "object",
        "slotType": "THREAT_EVIDENCE",
        "revealedWhen": "event.email_analysis",
        "summaryTemplate": "A handwritten envelope addressed to the victim contains a threatening note linked to [SUSPECT_NAME]",
        "assignment": {
          "targetCount": 1,
          "filters": ["canBeKiller=true"],
          "exclusive": true
        }
      },      
    {
      "id": "E4",
      "title": "Business Partnership Agreement",
      "type": "document",
      "slotType": "FINANCIAL_MOTIVE",
      "revealedWhen": "event.financial_investigation",
      "summaryTemplate": "Contract shows [SUSPECT_NAME] would gain control of business after victim's death",
      "assignment": {
        "targetCount": 1,
        "filters": ["canBeKiller=true"],
        "exclusive": true
      }
    },
    {
      "id": "E5",
      "title": "Social Media Post",
      "type": "document",
      "slotType": "DIGITAL_EVIDENCE",
      "revealedWhen": "event.digital_forensics",
      "summaryTemplate": "[SUSPECT_NAME] posted a cryptic message about 'getting even' before the crime",
      "assignment": {
        "targetCount": 3,
        "filters": ["canBeKiller=true"],
        "exclusive": false
      }
    },
    {
      "id": "E6",
      "title": "Insurance Policy",
      "type": "document",
      "slotType": "FINANCIAL_MOTIVE",
      "revealedWhen": "event.financial_investigation",
      "summaryTemplate": "[SUSPECT_NAME] is beneficiary of the victim's life insurance policy",
      "assignment": {
        "targetCount": 1,
        "filters": ["canBeKiller=true"],
        "exclusive": true
      }
    },
    {
      "id": "E7",
      "title": "Parking Garage Ticket",
      "type": "document",
      "slotType": "PHYSICAL_LINK",
      "revealedWhen": "event.scene_analysis",
      "summaryTemplate": "Parking ticket places [SUSPECT_NAME]'s vehicle near the crime scene",
      "assignment": {
        "targetCount": 2,
        "filters": ["canBeKiller=true"],
        "exclusive": false
      }
    },
    {
        "id": "E8",
        "title": "Burned Photo Fragment",
        "type": "object",
        "slotType": "PHYSICAL_LINK",
        "revealedWhen": "event.scene_analysis",
        "summaryTemplate": "A partially burned photo showing [SUSPECT_NAME] with the victim was found hidden among the debris",
        "assignment": {
          "targetCount": 1,
          "filters": ["canBeKiller=true"],
          "exclusive": true
        }
      },      
    {
      "id": "E9",
      "title": "Secret Relationship Evidence",
      "type": "document",
      "slotType": "PERSONAL_MOTIVE",
      "revealedWhen": "event.background_checks",
      "summaryTemplate": "Evidence reveals [SUSPECT_NAME] was having a secret affair with the victim's partner",
      "assignment": {
        "targetCount": 1,
        "filters": ["canBeKiller=true"],
        "exclusive": true
      }
    },
    {
      "id": "E10",
      "title": "Bloodied Clothing",
      "type": "object",
      "slotType": "PHYSICAL_LINK",
      "revealedWhen": "event.search_locations",
      "summaryTemplate": "Blood-stained clothing belonging to [SUSPECT_NAME] was found hidden",
      "assignment": {
        "targetCount": 1,
        "filters": ["canBeKiller=true"],
        "exclusive": true
      }
    },
    {
      "id": "E11",
      "title": "Blackmail Evidence",
      "type": "document",
      "slotType": "MOTIVE_EVIDENCE",
      "revealedWhen": "event.mid_investigation",
      "summaryTemplate": "Evidence found that the victim was blackmailing [SUSPECT_NAME]",
      "assignment": {
        "targetCount": 1,
        "filters": ["canBeKiller=true"],
        "exclusive": true
      }
    },
    {
      "id": "E12",
      "title": "Crime Scene Photo Analysis",
      "type": "image",
      "slotType": "FORENSIC",
      "revealedWhen": "event.scene_analysis",
      "summaryTemplate": "Enhanced photo shows an object belonging to [SUSPECT_NAME] at the scene",
      "assignment": {
        "targetCount": 1,
        "filters": ["canBeKiller=true"],
        "exclusive": true
      }
    },
    {
      "id": "E13",
      "title": "Voice Recording",
      "type": "document",
      "slotType": "WITNESS_ACCOUNT",
      "revealedWhen": "event.witness_interviews",
      "summaryTemplate": "Recording captures [SUSPECT_NAME] making threatening statements",
      "assignment": {
        "targetCount": 1,
        "filters": ["canBeKiller=true"],
        "exclusive": true
      }
    },
    {
      "id": "E14",
      "title": "Calendar Entry",
      "type": "document",
      "slotType": "OPPORTUNITY",
      "revealedWhen": "event.digital_forensics",
      "summaryTemplate": "[SUSPECT_NAME]'s calendar shows a meeting with the victim at the time of the murder",
      "assignment": {
        "targetCount": 1,
        "filters": ["canBeKiller=true"],
        "exclusive": true
      }
    },
    {
        "id": "E15",
        "title": "Bloodied Glove",
        "type": "object",
        "slotType": "PHYSICAL_LINK",
        "revealedWhen": "event.search_locations",
        "summaryTemplate": "A glove stained with blood was found, embroidered with the initial '[S]' matching [SUSPECT_NAME]'s belongings",
        "assignment": {
          "targetCount": 1,
          "filters": ["canBeKiller=true"],
          "exclusive": true
        }
      },
      {
        "id": "E16",
        "title": "Damaged Necklace Pendant",
        "type": "object",
        "slotType": "PHYSICAL_LINK",
        "revealedWhen": "event.scene_analysis",
        "summaryTemplate": "A broken pendant engraved with the initial '[S]' was found clenched in the victim's hand",
        "assignment": {
          "targetCount": 1,
          "filters": ["canBeKiller=true"],
          "exclusive": true
        }
      }
    
  ]
  